MANIFEST.in
setup.cfg
setup.py
tw/__init__.py
tw.mootools.egg-info/PKG-INFO
tw.mootools.egg-info/SOURCES.txt
tw.mootools.egg-info/dependency_links.txt
tw.mootools.egg-info/entry_points.txt
tw.mootools.egg-info/namespace_packages.txt
tw.mootools.egg-info/not-zip-safe
tw.mootools.egg-info/requires.txt
tw.mootools.egg-info/top_level.txt
tw/mootools/__init__.py
tw/mootools/base.py
tw/mootools/calendar.py
tw/mootools/dates.py
tw/mootools/defaults.py
tw/mootools/forms.py
tw/mootools/kwick.py
tw/mootools/mooeditable.py
tw/mootools/omnigrid.py
tw/mootools/release.py
tw/mootools/sortable.py
tw/mootools/widgets.py
tw/mootools/static/forms.js
tw/mootools/static/kwicks.js
tw/mootools/static/mootools-beta-1.2b2-compatible-compressed.js
tw/mootools/static/mootools-beta-1.2b2-compatible.js
tw/mootools/static/sortable.js
tw/mootools/static/1.2.1/mootools-1.2.1-core-jm.js
tw/mootools/static/1.2.1/mootools-1.2.1-core-nc.js
tw/mootools/static/1.2.1/mootools-1.2.1-core-yc.js
tw/mootools/static/1.2.1/mootools-1.2.1-more-jm.js
tw/mootools/static/1.2.1/mootools-1.2.1-more-nc.js
tw/mootools/static/1.2.1/mootools-1.2.1-more-yc.js
tw/mootools/static/1.2.4/mootools-1.2.4-core-jm.js
tw/mootools/static/1.2.4/mootools-1.2.4-core-nc.js
tw/mootools/static/1.2.4/mootools-1.2.4-core-yc.js
tw/mootools/static/1.2.4/mootools-1.2.4-more-jm.js
tw/mootools/static/1.2.4/mootools-1.2.4-more-nc.js
tw/mootools/static/1.2.4/mootools-1.2.4-more-yc.js
tw/mootools/static/calendar/mooECal.js
tw/mootools/static/calendar/style.css
tw/mootools/static/datepicker/DatePicker.css
tw/mootools/static/datepicker/DatePicker.js
tw/mootools/static/datepicker/date.gif
tw/mootools/static/datepicker/datefocus.gif
tw/mootools/static/formcheck/formcheck.js
tw/mootools/static/formcheck/lang/bg.js
tw/mootools/static/formcheck/lang/de.js
tw/mootools/static/formcheck/lang/en.js
tw/mootools/static/formcheck/lang/fr.js
tw/mootools/static/formcheck/lang/gr.js
tw/mootools/static/formcheck/lang/hu.js
tw/mootools/static/formcheck/lang/it.js
tw/mootools/static/formcheck/lang/jp.js
tw/mootools/static/formcheck/lang/nl.js
tw/mootools/static/formcheck/lang/pt.js
tw/mootools/static/formcheck/lang/ru.js
tw/mootools/static/formcheck/theme/classic/formcheck.css
tw/mootools/static/formcheck/theme/classic/img/b.png
