Metadata-Version: 1.0
Name: tw.mootools
Version: 0.9.8.2
Summary: ToscaWidgets wrapper for Mootools Javascript Toolkit
Home-page: http://toscawidgets.org/
Author: Christopher Perkins, Jonathan Schemoul
Author-email: chris@percious.com, jonathan.schemoul@jmsinfor.com
License: UNKNOWN
Download-URL: http://toscawidgets.org/download
Keywords: toscawidgets.widgets
Platform: UNKNOWN
Classifier: Development Status :: 4 - Beta
Classifier: Environment :: Web Environment
Classifier: Environment :: Web Environment :: ToscaWidgets
Classifier: Topic :: Software Development :: Libraries :: Python Modules
Classifier: Topic :: Software Development :: Widget Sets
Classifier: Intended Audience :: Developers
Classifier: Operating System :: OS Independent
Classifier: Programming Language :: Python
